README.md
setup.py
unimoddb/__init__.py
unimoddb/unimod.xml
unimoddb/unimoddb.py
unimoddb.egg-info/PKG-INFO
unimoddb.egg-info/SOURCES.txt
unimoddb.egg-info/dependency_links.txt
unimoddb.egg-info/requires.txt
unimoddb.egg-info/top_level.txt