Metadata-Version: 2.1
Name: unimoddb
Version: 0.1.3
Summary: A library for SQLite access to the Unimod modification database
Home-page: https://github.com/ikcgroup/unimoddb
Author: Daniel Spencer
Author-email: danielspencer305@hotmail.co.uk
License: MIT
Keywords: UNIMOD,PROTEOMICS
Platform: UNKNOWN
Classifier: Development Status :: 4 - Beta
Classifier: Intended Audience :: Developers
Classifier: Topic :: Scientific/Engineering :: Bio-Informatics
Classifier: License :: OSI Approved :: MIT License
Classifier: Programming Language :: Python :: 3
Classifier: Programming Language :: Python :: 3.7
Classifier: Programming Language :: Python :: 3.8
